jupyterquest/__init__.py
jupyterquest/autograder.py
jupyterquest/code_quality_check.py
jupyterquest/code_style_check.py
jupyterquest/commit_analysis.py
jupyterquest/dependency_checks.py
jupyterquest/generate_markdown_report.py
jupyterquest/parse_ipynb.py
jupyterquest/repo_structure_check.py
jupyterquest/security_checks.py
jupyterquest-0.3.0.dist-info/LICENSE
jupyterquest-0.3.0.dist-info/METADATA
jupyterquest-0.3.0.dist-info/WHEEL
jupyterquest-0.3.0.dist-info/top_level.txt
jupyterquest-0.3.0.dist-info/RECORD
