Metadata-Version: 2.1
Name: jupyterquest
Version: 0.3.0
Summary: A Python package for automating grading of Jupyter notebook files.
Author-email: Greg Chism <gchism@arizona.edu>
License: MIT License
Project-URL: Source, https://github.com/Gchism94/jupyterquest
Project-URL: Tracker, https://github.com/Gchism94/jupyterquest/issues
Keywords: education,autograder,jupyter,notebook
Classifier: Programming Language :: Python :: 3
Classifier: License :: OSI Approved :: MIT License
Classifier: Operating System :: OS Independent
Requires-Python: >=3.8
License-File: LICENSE
Requires-Dist: radon >=6.0.1
Requires-Dist: GitPython >=3.1.41
Requires-Dist: markdown >=3.5.2
Requires-Dist: flake8 >=3.9.0
Requires-Dist: pylint >=2.9.6
Requires-Dist: pandoc >=2.3
Requires-Dist: pytest >=6.2.5
Requires-Dist: jupyter >=1.0.0
Requires-Dist: nbformat >=5.9.2
Requires-Dist: requests >=2.25.1
Requires-Dist: safety >=3.0.1
Requires-Dist: pip-audit >=2.7.2
Requires-Dist: bandit >=1.7.7
